python_tmx/__init__.py
python_tmx/py.typed
python_tmx-0.4.2.dist-info/METADATA
python_tmx-0.4.2.dist-info/WHEEL
python_tmx-0.4.2.dist-info/top_level.txt
python_tmx-0.4.2.dist-info/RECORD
