Metadata-Version: 2.4
Name: python-tmx
Version: 0.4.2
Summary: DEPRECATED: renamed to 'hypomnema'. Install 'hypomnema'.
Author-email: Enzo Agosta <agosta.enzowork@gmail.com>
License: MIT
Project-URL: Homepage, https://pypi.org/project/hypomnema/
Project-URL: Source, https://github.com/EnzoAgosta/hypomnema
Project-URL: Issues, https://github.com/EnzoAgosta/hypomnema/issues
Classifier: Development Status :: 7 - Inactive
Classifier: Intended Audience :: Developers
Classifier: License :: OSI Approved :: MIT License
Classifier: Operating System :: OS Independent
Classifier: Programming Language :: Python :: 3.12
Classifier: Programming Language :: Python :: 3.13
Classifier: Programming Language :: Python :: 3.14
Classifier: Topic :: Text Processing :: Linguistic
Requires-Python: >=3.12
Requires-Dist: hypomnema<1,>=0.4.2
